orgnote/__init__.py
orgnote/__main__.py
orgnote/colorsrc.py
orgnote/config.py
orgnote/init.py
orgnote/parser.py
orgnote/util.py
orgnote-1.0.7.dist-info/LICENSE
orgnote-1.0.7.dist-info/METADATA
orgnote-1.0.7.dist-info/WHEEL
orgnote-1.0.7.dist-info/entry_points.txt
orgnote-1.0.7.dist-info/top_level.txt
orgnote-1.0.7.dist-info/RECORD
