Metadata-Version: 2.1
Name: orgnote
Version: 1.0.7
Summary: A simple blog based on org-mode
Home-page: https://github.com/LeslieZhu/OrgNote
Author: Leslie Zhu
Author-email: pythonisland@gmail.com
License: GPL
Keywords: org-mode,emacs,orgnote,blog
Platform: linux
Classifier: Programming Language :: Python
Classifier: Programming Language :: Python :: 2.7
Classifier: Programming Language :: Python :: 3.5
Classifier: Programming Language :: Python :: 3.7
Classifier: Environment :: Other Environment
Classifier: Intended Audience :: Developers
Classifier: Operating System :: OS Independent
Classifier: Topic :: Software Development :: Libraries :: Python Modules
Classifier: Topic :: Text Processing :: Linguistic
License-File: LICENSE
Requires-Dist: pyyaml >=4.2b1
Requires-Dist: Pygments >=2.7.4
Requires-Dist: beautifulsoup4 >=4.4.1
Requires-Dist: bs4 >=0.0.1
Requires-Dist: mistune ==2.0.4
Requires-Dist: Markdown >=3.1.1
Requires-Dist: watchdog >=0.9.0
